{
  "info": {
    "contact": null,
    "description": null,
    "extensions": {
      "changed": {
        "x-github-release": {
          "from": 3.8,
          "to": 3.7
        }
      }
    },
    "license": null,
    "terms_of_service": null,
    "title": null,
    "version": null
  },
  "paths": {
    "changed": {
      "/admin/tokens": {
        "get": {
          "responses": {
            "changed": {
              "200": {
                "content": {
                  "changed": {
                    "application/json": {
                      "schema_changed": {
                        "items_changed": {
                          "properties_changed": {
                            "changed": {
                              "installation": {
                                "properties_changed": {
                                  "changed": {
                                    "permissions": {
                                      "properties_changed": {
                                        "removed": [
                                          "organization_announcement_banners"
                                        ]
                                      }
                                    }
                                  }
                                }
                              }
                            }
                          }
                        }
                      }
                    }
                  }
                }
              }
            }
          }
        }
      },
      "/admin/users/{username}/authorizations": {
        "post": {
          "responses": {
            "changed": {
              "200": {
                "content": {
                  "changed": {
                    "application/json": {
                      "schema_changed": {
                        "properties_changed": {
                          "changed": {
                            "installation": {
                              "properties_changed": {
                                "changed": {
                                  "permissions": {
                                    "properties_changed": {
                                      "removed": [
                                        "organization_announcement_banners"
                                      ]
                                    }
                                  }
                                }
                              }
                            }
                          }
                        }
                      }
                    }
                  }
                }
              },
              "201": {
                "content": {
                  "changed": {
                    "application/json": {
                      "schema_changed": {
                        "properties_changed": {
                          "changed": {
                            "installation": {
                              "properties_changed": {
                                "changed": {
                                  "permissions": {
                                    "properties_changed": {
                                      "removed": [
                                        "organization_announcement_banners"
                                      ]
                                    }
                                  }
                                }
                              }
                            }
                          }
                        }
                      }
                    }
                  }
                }
              }
            }
          }
        }
      },
      "/app/installations": {
        "get": {
          "responses": {
            "changed": {
              "200": {
                "content": {
                  "changed": {
                    "application/json": {
                      "schema_changed": {
                        "items_changed": {
                          "properties_changed": {
                            "changed": {
                              "permissions": {
                                "properties_changed": {
                                  "removed": [
                                    "organization_announcement_banners"
                                  ]
                                }
                              }
                            }
                          }
                        }
                      }
                    }
                  }
                }
              }
            }
          }
        }
      },
      "/app/installations/{installation_id}": {
        "get": {
          "responses": {
            "changed": {
              "200": {
                "content": {
                  "changed": {
                    "application/json": {
                      "schema_changed": {
                        "properties_changed": {
                          "changed": {
                            "permissions": {
                              "properties_changed": {
                                "removed": [
                                  "organization_announcement_banners"
                                ]
                              }
                            }
                          }
                        }
                      }
                    }
                  }
                }
              }
            }
          }
        }
      },
      "/app/installations/{installation_id}/access_tokens": {
        "post": {
          "request_body": {
            "content_changed": {
              "changed": {
                "application/json": {
                  "schema_changed": {
                    "properties_changed": {
                      "changed": {
                        "permissions": {
                          "properties_changed": {
                            "removed": [
                              "organization_announcement_banners"
                            ]
                          }
                        }
                      }
                    }
                  }
                }
              }
            }
          },
          "responses": {
            "changed": {
              "201": {
                "content": {
                  "changed": {
                    "application/json": {
                      "schema_changed": {
                        "properties_changed": {
                          "changed": {
                            "permissions": {
                              "properties_changed": {
                                "removed": [
                                  "organization_announcement_banners"
                                ]
                              }
                            }
                          }
                        }
                      }
                    }
                  }
                }
              }
            }
          }
        }
      },
      "/applications/{client_id}/token": {
        "patch": {
          "responses": {
            "changed": {
              "200": {
                "content": {
                  "changed": {
                    "application/json": {
                      "schema_changed": {
                        "properties_changed": {
                          "changed": {
                            "installation": {
                              "properties_changed": {
                                "changed": {
                                  "permissions": {
                                    "properties_changed": {
                                      "removed": [
                                        "organization_announcement_banners"
                                      ]
                                    }
                                  }
                                }
                              }
                            }
                          }
                        }
                      }
                    }
                  }
                }
              }
            }
          }
        },
        "post": {
          "responses": {
            "changed": {
              "200": {
                "content": {
                  "changed": {
                    "application/json": {
                      "schema_changed": {
                        "properties_changed": {
                          "changed": {
                            "installation": {
                              "properties_changed": {
                                "changed": {
                                  "permissions": {
                                    "properties_changed": {
                                      "removed": [
                                        "organization_announcement_banners"
                                      ]
                                    }
                                  }
                                }
                              }
                            }
                          }
                        }
                      }
                    }
                  }
                }
              }
            }
          }
        }
      },
      "/applications/{client_id}/token/scoped": {
        "post": {
          "request_body": {
            "content_changed": {
              "changed": {
                "application/json": {
                  "schema_changed": {
                    "properties_changed": {
                      "changed": {
                        "permissions": {
                          "properties_changed": {
                            "removed": [
                              "organization_announcement_banners"
                            ]
                          }
                        }
                      }
                    }
                  }
                }
              }
            }
          },
          "responses": {
            "changed": {
              "200": {
                "content": {
                  "changed": {
                    "application/json": {
                      "schema_changed": {
                        "properties_changed": {
                          "changed": {
                            "installation": {
                              "properties_changed": {
                                "changed": {
                                  "permissions": {
                                    "properties_changed": {
                                      "removed": [
                                        "organization_announcement_banners"
                                      ]
                                    }
                                  }
                                }
                              }
                            }
                          }
                        }
                      }
                    }
                  }
                }
              }
            }
          }
        }
      },
      "/authorizations": {
        "get": {
          "responses": {
            "changed": {
              "200": {
                "content": {
                  "changed": {
                    "application/json": {
                      "schema_changed": {
                        "items_changed": {
                          "properties_changed": {
                            "changed": {
                              "installation": {
                                "properties_changed": {
                                  "changed": {
                                    "permissions": {
                                      "properties_changed": {
                                        "removed": [
                                          "organization_announcement_banners"
                                        ]
                                      }
                                    }
                                  }
                                }
                              }
                            }
                          }
                        }
                      }
                    }
                  }
                }
              }
            }
          }
        },
        "post": {
          "responses": {
            "changed": {
              "201": {
                "content": {
                  "changed": {
                    "application/json": {
                      "schema_changed": {
                        "properties_changed": {
                          "changed": {
                            "installation": {
                              "properties_changed": {
                                "changed": {
                                  "permissions": {
                                    "properties_changed": {
                                      "removed": [
                                        "organization_announcement_banners"
                                      ]
                                    }
                                  }
                                }
                              }
                            }
                          }
                        }
                      }
                    }
                  }
                }
              }
            }
          }
        }
      },
      "/authorizations/clients/{client_id}": {
        "put": {
          "responses": {
            "changed": {
              "200": {
                "content": {
                  "changed": {
                    "application/json": {
                      "schema_changed": {
                        "properties_changed": {
                          "changed": {
                            "installation": {
                              "properties_changed": {
                                "changed": {
                                  "permissions": {
                                    "properties_changed": {
                                      "removed": [
                                        "organization_announcement_banners"
                                      ]
                                    }
                                  }
                                }
                              }
                            }
                          }
                        }
                      }
                    }
                  }
                }
              },
              "201": {
                "content": {
                  "changed": {
                    "application/json": {
                      "schema_changed": {
                        "properties_changed": {
                          "changed": {
                            "installation": {
                              "properties_changed": {
                                "changed": {
                                  "permissions": {
                                    "properties_changed": {
                                      "removed": [
                                        "organization_announcement_banners"
                                      ]
                                    }
                                  }
                                }
                              }
                            }
                          }
                        }
                      }
                    }
                  }
                }
              }
            }
          }
        }
      },
      "/authorizations/clients/{client_id}/{fingerprint}": {
        "put": {
          "responses": {
            "changed": {
              "200": {
                "content": {
                  "changed": {
                    "application/json": {
                      "schema_changed": {
                        "properties_changed": {
                          "changed": {
                            "installation": {
                              "properties_changed": {
                                "changed": {
                                  "permissions": {
                                    "properties_changed": {
                                      "removed": [
                                        "organization_announcement_banners"
                                      ]
                                    }
                                  }
                                }
                              }
                            }
                          }
                        }
                      }
                    }
                  }
                }
              },
              "201": {
                "content": {
                  "changed": {
                    "application/json": {
                      "schema_changed": {
                        "properties_changed": {
                          "changed": {
                            "installation": {
                              "properties_changed": {
                                "changed": {
                                  "permissions": {
                                    "properties_changed": {
                                      "removed": [
                                        "organization_announcement_banners"
                                      ]
                                    }
                                  }
                                }
                              }
                            }
                          }
                        }
                      }
                    }
                  }
                }
              }
            }
          }
        }
      },
      "/authorizations/{authorization_id}": {
        "get": {
          "responses": {
            "changed": {
              "200": {
                "content": {
                  "changed": {
                    "application/json": {
                      "schema_changed": {
                        "properties_changed": {
                          "changed": {
                            "installation": {
                              "properties_changed": {
                                "changed": {
                                  "permissions": {
                                    "properties_changed": {
                                      "removed": [
                                        "organization_announcement_banners"
                                      ]
                                    }
                                  }
                                }
                              }
                            }
                          }
                        }
                      }
                    }
                  }
                }
              }
            }
          }
        },
        "patch": {
          "responses": {
            "changed": {
              "200": {
                "content": {
                  "changed": {
                    "application/json": {
                      "schema_changed": {
                        "properties_changed": {
                          "changed": {
                            "installation": {
                              "properties_changed": {
                                "changed": {
                                  "permissions": {
                                    "properties_changed": {
                                      "removed": [
                                        "organization_announcement_banners"
                                      ]
                                    }
                                  }
                                }
                              }
                            }
                          }
                        }
                      }
                    }
                  }
                }
              }
            }
          }
        }
      },
      "/enterprises/{enterprise}/secret-scanning/alerts": {
        "get": {
          "responses": {
            "changed": {
              "200": {
                "content": {
                  "changed": {
                    "application/json": {
                      "schema_changed": {
                        "items_changed": {
                          "properties_changed": {
                            "removed": [
                              "resolution_comment"
                            ]
                          }
                        }
                      }
                    }
                  }
                }
              }
            }
          }
        }
      },
      "/notifications": {
        "get": {
          "responses": {
            "changed": {
              "200": {
                "content": {
                  "changed": {
                    "application/json": {
                      "schema_changed": {
                        "items_changed": {
                          "properties_changed": {
                            "changed": {
                              "repository": {
                                "properties_changed": {
                                  "removed": [
                                    "security_and_analysis"
                                  ]
                                }
                              }
                            }
                          }
                        }
                      }
                    }
                  }
                }
              }
            }
          }
        }
      },
      "/notifications/threads/{thread_id}": {
        "get": {
          "responses": {
            "changed": {
              "200": {
                "content": {
                  "changed": {
                    "application/json": {
                      "schema_changed": {
                        "properties_changed": {
                          "changed": {
                            "repository": {
                              "properties_changed": {
                                "removed": [
                                  "security_and_analysis"
                                ]
                              }
                            }
                          }
                        }
                      }
                    }
                  }
                }
              }
            }
          }
        }
      },
      "/orgs/{org}": {
        "get": {
          "responses": {
            "changed": {
              "200": {
                "content": {
                  "changed": {
                    "application/json": {
                      "schema_changed": {
                        "properties_changed": {
                          "removed": [
                            "secret_scanning_push_protection_custom_link",
                            "secret_scanning_push_protection_custom_link_enabled"
                          ]
                        }
                      }
                    }
                  }
                }
              }
            }
          }
        },
        "patch": {
          "request_body": {
            "content_changed": {
              "changed": {
                "application/json": {
                  "schema_changed": {
                    "properties_changed": {
                      "removed": [
                        "secret_scanning_push_protection_custom_link",
                        "secret_scanning_push_protection_custom_link_enabled"
                      ]
                    }
                  }
                }
              }
            }
          },
          "responses": {
            "changed": {
              "200": {
                "content": {
                  "changed": {
                    "application/json": {
                      "schema_changed": {
                        "properties_changed": {
                          "removed": [
                            "secret_scanning_push_protection_custom_link",
                            "secret_scanning_push_protection_custom_link_enabled"
                          ]
                        }
                      }
                    }
                  }
                }
              }
            }
          }
        }
      },
      "/orgs/{org}/actions/runner-groups/{runner_group_id}/repositories": {
        "get": {
          "responses": {
            "changed": {
              "200": {
                "content": {
                  "changed": {
                    "application/json": {
                      "schema_changed": {
                        "properties_changed": {
                          "changed": {
                            "repositories": {
                              "items_changed": {
                                "properties_changed": {
                                  "removed": [
                                    "security_and_analysis"
                                  ]
                                }
                              }
                            }
                          }
                        }
                      }
                    }
                  }
                }
              }
            }
          }
        }
      },
      "/orgs/{org}/actions/secrets/{secret_name}/repositories": {
        "get": {
          "responses": {
            "changed": {
              "200": {
                "content": {
                  "changed": {
                    "application/json": {
                      "schema_changed": {
                        "properties_changed": {
                          "changed": {
                            "repositories": {
                              "items_changed": {
                                "properties_changed": {
                                  "removed": [
                                    "security_and_analysis"
                                  ]
                                }
                              }
                            }
                          }
                        }
                      }
                    }
                  }
                }
              }
            }
          }
        }
      },
      "/orgs/{org}/code-scanning/alerts": {
        "get": {
          "parameters": {
            "removed": [
              {
                "description": "If specified, only code scanning alerts with this severity will be returned.",
                "in": "query",
                "name": "severity",
                "required": false,
                "schema": {
                  "description": "Severity of a code scanning alert.",
                  "enum": [
                    "critical",
                    "high",
                    "medium",
                    "low",
                    "warning",
                    "note",
                    "error"
                  ],
                  "type": "string"
                },
                "style": "form"
              }
            ]
          }
        }
      },
      "/orgs/{org}/dependabot/secrets/{secret_name}/repositories": {
        "get": {
          "responses": {
            "changed": {
              "200": {
                "content": {
                  "changed": {
                    "application/json": {
                      "schema_changed": {
                        "properties_changed": {
                          "changed": {
                            "repositories": {
                              "items_changed": {
                                "properties_changed": {
                                  "removed": [
                                    "security_and_analysis"
                                  ]
                                }
                              }
                            }
                          }
                        }
                      }
                    }
                  }
                }
              }
            }
          }
        }
      },
      "/orgs/{org}/installation": {
        "get": {
          "responses": {
            "changed": {
              "200": {
                "content": {
                  "changed": {
                    "application/json": {
                      "schema_changed": {
                        "properties_changed": {
                          "changed": {
                            "permissions": {
                              "properties_changed": {
                                "removed": [
                                  "organization_announcement_banners"
                                ]
                              }
                            }
                          }
                        }
                      }
                    }
                  }
                }
              }
            }
          }
        }
      },
      "/orgs/{org}/installations": {
        "get": {
          "responses": {
            "changed": {
              "200": {
                "content": {
                  "changed": {
                    "application/json": {
                      "schema_changed": {
                        "properties_changed": {
                          "changed": {
                            "installations": {
                              "items_changed": {
                                "properties_changed": {
                                  "changed": {
                                    "permissions": {
                                      "properties_changed": {
                                        "removed": [
                                          "organization_announcement_banners"
                                        ]
                                      }
                                    }
                                  }
                                }
                              }
                            }
                          }
                        }
                      }
                    }
                  }
                }
              }
            }
          }
        }
      },
      "/orgs/{org}/migrations/{migration_id}/repositories": {
        "get": {
          "responses": {
            "changed": {
              "200": {
                "content": {
                  "changed": {
                    "application/json": {
                      "schema_changed": {
                        "items_changed": {
                          "properties_changed": {
                            "removed": [
                              "security_and_analysis"
                            ]
                          }
                        }
                      }
                    }
                  }
                }
              }
            }
          }
        }
      },
      "/orgs/{org}/repos": {
        "get": {
          "responses": {
            "changed": {
              "200": {
                "content": {
                  "changed": {
                    "application/json": {
                      "schema_changed": {
                        "items_changed": {
                          "properties_changed": {
                            "removed": [
                              "security_and_analysis"
                            ]
                          }
                        }
                      }
                    }
                  }
                }
              }
            }
          }
        }
      },
      "/orgs/{org}/secret-scanning/alerts": {
        "get": {
          "responses": {
            "changed": {
              "200": {
                "content": {
                  "changed": {
                    "application/json": {
                      "schema_changed": {
                        "items_changed": {
                          "properties_changed": {
                            "removed": [
                              "resolution_comment"
                            ]
                          }
                        }
                      }
                    }
                  }
                }
              }
            }
          }
        }
      },
      "/orgs/{org}/teams/{team_slug}/repos": {
        "get": {
          "responses": {
            "changed": {
              "200": {
                "content": {
                  "changed": {
                    "application/json": {
                      "schema_changed": {
                        "items_changed": {
                          "properties_changed": {
                            "removed": [
                              "security_and_analysis"
                            ]
                          }
                        }
                      }
                    }
                  }
                }
              }
            }
          }
        }
      },
      "/repos/{owner}/{repo}/actions/artifacts": {
        "get": {
          "parameters": {
            "removed": [
              {
                "description": "Filters artifacts by exact match on their name field.",
                "in": "query",
                "name": "name",
                "required": false,
                "schema": {
                  "type": "string"
                },
                "style": "form"
              }
            ]
          }
        }
      },
      "/repos/{owner}/{repo}/actions/jobs/{job_id}": {
        "get": {
          "responses": {
            "changed": {
              "200": {
                "content": {
                  "changed": {
                    "application/json": {
                      "schema_changed": {
                        "properties_changed": {
                          "removed": [
                            "head_branch",
                            "workflow_name"
                          ]
                        }
                      }
                    }
                  }
                }
              }
            }
          }
        }
      },
      "/repos/{owner}/{repo}/actions/oidc/customization/sub": {
        "put": {
          "request_body": {
            "content_changed": {
              "changed": {
                "application/json": {
                  "schema_changed": {
                    "properties_changed": {
                      "removed": [
                        "include_claim_keys"
                      ]
                    }
                  }
                }
              }
            }
          }
        }
      },
      "/repos/{owner}/{repo}/actions/permissions/access": {
        "get": {
          "responses": {
            "changed": {
              "200": {
                "content": {
                  "changed": {
                    "application/json": {
                      "schema_changed": {
                        "properties_changed": {
                          "changed": {
                            "access_level": {
                              "enum_changed": {
                                "added": false,
                                "removed": false,
                                "values_removed": [
                                  "user"
                                ]
                              }
                            }
                          }
                        }
                      }
                    }
                  }
                }
              }
            }
          }
        },
        "put": {
          "request_body": {
            "content_changed": {
              "changed": {
                "application/json": {
                  "schema_changed": {
                    "properties_changed": {
                      "changed": {
                        "access_level": {
                          "enum_changed": {
                            "added": false,
                            "removed": false,
                            "values_removed": [
                              "user"
                            ]
                          }
                        }
                      }
                    }
                  }
                }
              }
            }
          }
        }
      },
      "/repos/{owner}/{repo}/actions/runs": {
        "get": {
          "responses": {
            "changed": {
              "200": {
                "content": {
                  "changed": {
                    "application/json": {
                      "schema_changed": {
                        "properties_changed": {
                          "changed": {
                            "workflow_runs": {
                              "items_changed": {
                                "properties_changed": {
                                  "changed": {
                                    "head_repository": {
                                      "properties_changed": {
                                        "removed": [
                                          "security_and_analysis"
                                        ]
                                      }
                                    },
                                    "repository": {
                                      "properties_changed": {
                                        "removed": [
                                          "security_and_analysis"
                                        ]
                                      }
                                    }
                                  },
                                  "removed": [
                                    "display_title"
                                  ]
                                }
                              }
                            }
                          }
                        }
                      }
                    }
                  }
                }
              }
            }
          }
        }
      },
      "/repos/{owner}/{repo}/actions/runs/{run_id}": {
        "get": {
          "responses": {
            "changed": {
              "200": {
                "content": {
                  "changed": {
                    "application/json": {
                      "schema_changed": {
                        "properties_changed": {
                          "changed": {
                            "head_repository": {
                              "properties_changed": {
                                "removed": [
                                  "security_and_analysis"
                                ]
                              }
                            },
                            "repository": {
                              "properties_changed": {
                                "removed": [
                                  "security_and_analysis"
                                ]
                              }
                            }
                          },
                          "removed": [
                            "display_title"
                          ]
                        }
                      }
                    }
                  }
                }
              }
            }
          }
        }
      },
      "/repos/{owner}/{repo}/actions/runs/{run_id}/attempts/{attempt_number}": {
        "get": {
          "responses": {
            "changed": {
              "200": {
                "content": {
                  "changed": {
                    "application/json": {
                      "schema_changed": {
                        "properties_changed": {
                          "changed": {
                            "head_repository": {
                              "properties_changed": {
                                "removed": [
                                  "security_and_analysis"
                                ]
                              }
                            },
                            "repository": {
                              "properties_changed": {
                                "removed": [
                                  "security_and_analysis"
                                ]
                              }
                            }
                          },
                          "removed": [
                            "display_title"
                          ]
                        }
                      }
                    }
                  }
                }
              }
            }
          }
        }
      },
      "/repos/{owner}/{repo}/actions/runs/{run_id}/attempts/{attempt_number}/jobs": {
        "get": {
          "responses": {
            "changed": {
              "200": {
                "content": {
                  "changed": {
                    "application/json": {
                      "schema_changed": {
                        "properties_changed": {
                          "changed": {
                            "jobs": {
                              "items_changed": {
                                "properties_changed": {
                                  "removed": [
                                    "head_branch",
                                    "workflow_name"
                                  ]
                                }
                              }
                            }
                          }
                        }
                      }
                    }
                  }
                }
              }
            }
          }
        }
      },
      "/repos/{owner}/{repo}/actions/runs/{run_id}/jobs": {
        "get": {
          "responses": {
            "changed": {
              "200": {
                "content": {
                  "changed": {
                    "application/json": {
                      "schema_changed": {
                        "properties_changed": {
                          "changed": {
                            "jobs": {
                              "items_changed": {
                                "properties_changed": {
                                  "removed": [
                                    "head_branch",
                                    "workflow_name"
                                  ]
                                }
                              }
                            }
                          }
                        }
                      }
                    }
                  }
                }
              }
            }
          }
        }
      },
      "/repos/{owner}/{repo}/actions/workflows/{workflow_id}/runs": {
        "get": {
          "responses": {
            "changed": {
              "200": {
                "content": {
                  "changed": {
                    "application/json": {
                      "schema_changed": {
                        "properties_changed": {
                          "changed": {
                            "workflow_runs": {
                              "items_changed": {
                                "properties_changed": {
                                  "changed": {
                                    "head_repository": {
                                      "properties_changed": {
                                        "removed": [
                                          "security_and_analysis"
                                        ]
                                      }
                                    },
                                    "repository": {
                                      "properties_changed": {
                                        "removed": [
                                          "security_and_analysis"
                                        ]
                                      }
                                    }
                                  },
                                  "removed": [
                                    "display_title"
                                  ]
                                }
                              }
                            }
                          }
                        }
                      }
                    }
                  }
                }
              }
            }
          }
        }
      },
      "/repos/{owner}/{repo}/branches": {
        "get": {
          "responses": {
            "changed": {
              "200": {
                "content": {
                  "changed": {
                    "application/json": {
                      "schema_changed": {
                        "items_changed": {
                          "properties_changed": {
                            "changed": {
                              "protection": {
                                "properties_changed": {
                                  "changed": {
                                    "required_pull_request_reviews": {
                                      "properties_changed": {
                                        "removed": [
                                          "require_last_push_approval"
                                        ]
                                      }
                                    }
                                  },
                                  "removed": [
                                    "allow_fork_syncing",
                                    "lock_branch"
                                  ]
                                }
                              }
                            }
                          }
                        }
                      }
                    }
                  }
                }
              }
            }
          }
        }
      },
      "/repos/{owner}/{repo}/branches/{branch}": {
        "get": {
          "responses": {
            "changed": {
              "200": {
                "content": {
                  "changed": {
                    "application/json": {
                      "schema_changed": {
                        "properties_changed": {
                          "changed": {
                            "protection": {
                              "properties_changed": {
                                "changed": {
                                  "required_pull_request_reviews": {
                                    "properties_changed": {
                                      "removed": [
                                        "require_last_push_approval"
                                      ]
                                    }
                                  }
                                },
                                "removed": [
                                  "allow_fork_syncing",
                                  "lock_branch"
                                ]
                              }
                            }
                          }
                        }
                      }
                    }
                  }
                }
              }
            }
          }
        }
      },
      "/repos/{owner}/{repo}/branches/{branch}/protection": {
        "get": {
          "responses": {
            "changed": {
              "200": {
                "content": {
                  "changed": {
                    "application/json": {
                      "schema_changed": {
                        "properties_changed": {
                          "changed": {
                            "required_pull_request_reviews": {
                              "properties_changed": {
                                "removed": [
                                  "require_last_push_approval"
                                ]
                              }
                            }
                          },
                          "removed": [
                            "allow_fork_syncing",
                            "lock_branch"
                          ]
                        }
                      }
                    }
                  }
                }
              }
            }
          }
        },
        "put": {
          "request_body": {
            "content_changed": {
              "changed": {
                "application/json": {
                  "schema_changed": {
                    "properties_changed": {
                      "changed": {
                        "required_pull_request_reviews": {
                          "properties_changed": {
                            "removed": [
                              "require_last_push_approval"
                            ]
                          }
                        }
                      },
                      "removed": [
                        "allow_fork_syncing",
                        "lock_branch"
                      ]
                    }
                  }
                }
              }
            }
          },
          "responses": {
            "changed": {
              "200": {
                "content": {
                  "changed": {
                    "application/json": {
                      "schema_changed": {
                        "properties_changed": {
                          "changed": {
                            "required_pull_request_reviews": {
                              "properties_changed": {
                                "removed": [
                                  "require_last_push_approval"
                                ]
                              }
                            }
                          },
                          "removed": [
                            "allow_fork_syncing",
                            "lock_branch"
                          ]
                        }
                      }
                    }
                  }
                }
              }
            }
          }
        }
      },
      "/repos/{owner}/{repo}/branches/{branch}/protection/required_pull_request_reviews": {
        "get": {
          "responses": {
            "changed": {
              "200": {
                "content": {
                  "changed": {
                    "application/json": {
                      "schema_changed": {
                        "properties_changed": {
                          "removed": [
                            "require_last_push_approval"
                          ]
                        }
                      }
                    }
                  }
                }
              }
            }
          }
        },
        "patch": {
          "request_body": {
            "content_changed": {
              "changed": {
                "application/json": {
                  "schema_changed": {
                    "properties_changed": {
                      "removed": [
                        "require_last_push_approval"
                      ]
                    }
                  }
                }
              }
            }
          },
          "responses": {
            "changed": {
              "200": {
                "content": {
                  "changed": {
                    "application/json": {
                      "schema_changed": {
                        "properties_changed": {
                          "removed": [
                            "require_last_push_approval"
                          ]
                        }
                      }
                    }
                  }
                }
              }
            }
          }
        }
      },
      "/repos/{owner}/{repo}/branches/{branch}/rename": {
        "post": {
          "responses": {
            "changed": {
              "201": {
                "content": {
                  "changed": {
                    "application/json": {
                      "schema_changed": {
                        "properties_changed": {
                          "changed": {
                            "protection": {
                              "properties_changed": {
                                "changed": {
                                  "required_pull_request_reviews": {
                                    "properties_changed": {
                                      "removed": [
                                        "require_last_push_approval"
                                      ]
                                    }
                                  }
                                },
                                "removed": [
                                  "allow_fork_syncing",
                                  "lock_branch"
                                ]
                              }
                            }
                          }
                        }
                      }
                    }
                  }
                }
              }
            }
          }
        }
      },
      "/repos/{owner}/{repo}/check-suites": {
        "post": {
          "responses": {
            "changed": {
              "200": {
                "content": {
                  "changed": {
                    "application/json": {
                      "schema_changed": {
                        "properties_changed": {
                          "changed": {
                            "repository": {
                              "properties_changed": {
                                "removed": [
                                  "security_and_analysis"
                                ]
                              }
                            }
                          }
                        }
                      }
                    }
                  }
                }
              },
              "201": {
                "content": {
                  "changed": {
                    "application/json": {
                      "schema_changed": {
                        "properties_changed": {
                          "changed": {
                            "repository": {
                              "properties_changed": {
                                "removed": [
                                  "security_and_analysis"
                                ]
                              }
                            }
                          }
                        }
                      }
                    }
                  }
                }
              }
            }
          }
        }
      },
      "/repos/{owner}/{repo}/check-suites/preferences": {
        "patch": {
          "responses": {
            "changed": {
              "200": {
                "content": {
                  "changed": {
                    "application/json": {
                      "schema_changed": {
                        "properties_changed": {
                          "changed": {
                            "repository": {
                              "properties_changed": {
                                "removed": [
                                  "security_and_analysis"
                                ]
                              }
                            }
                          }
                        }
                      }
                    }
                  }
                }
              }
            }
          }
        }
      },
      "/repos/{owner}/{repo}/check-suites/{check_suite_id}": {
        "get": {
          "responses": {
            "changed": {
              "200": {
                "content": {
                  "changed": {
                    "application/json": {
                      "schema_changed": {
                        "properties_changed": {
                          "changed": {
                            "repository": {
                              "properties_changed": {
                                "removed": [
                                  "security_and_analysis"
                                ]
                              }
                            }
                          }
                        }
                      }
                    }
                  }
                }
              }
            }
          }
        }
      },
      "/repos/{owner}/{repo}/collaborators": {
        "get": {
          "parameters": {
            "removed": [
              {
                "description": "Filter collaborators by the permissions they have on the repository. If not specified, all collaborators will be returned.",
                "in": "query",
                "name": "permission",
                "required": false,
                "schema": {
                  "enum": [
                    "pull",
                    "triage",
                    "push",
                    "maintain",
                    "admin"
                  ],
                  "type": "string"
                },
                "style": "form"
              }
            ]
          }
        }
      },
      "/repos/{owner}/{repo}/collaborators/{username}": {
        "put": {
          "responses": {
            "changed": {
              "201": {
                "content": {
                  "changed": {
                    "application/json": {
                      "schema_changed": {
                        "properties_changed": {
                          "changed": {
                            "repository": {
                              "properties_changed": {
                                "removed": [
                                  "security_and_analysis"
                                ]
                              }
                            }
                          }
                        }
                      }
                    }
                  }
                }
              }
            }
          }
        }
      },
      "/repos/{owner}/{repo}/commits/{ref}/check-suites": {
        "get": {
          "responses": {
            "changed": {
              "200": {
                "content": {
                  "changed": {
                    "application/json": {
                      "schema_changed": {
                        "properties_changed": {
                          "changed": {
                            "check_suites": {
                              "items_changed": {
                                "properties_changed": {
                                  "changed": {
                                    "repository": {
                                      "properties_changed": {
                                        "removed": [
                                          "security_and_analysis"
                                        ]
                                      }
                                    }
                                  }
                                }
                              }
                            }
                          }
                        }
                      }
                    }
                  }
                }
              }
            }
          }
        }
      },
      "/repos/{owner}/{repo}/commits/{ref}/status": {
        "get": {
          "responses": {
            "changed": {
              "200": {
                "content": {
                  "changed": {
                    "application/json": {
                      "schema_changed": {
                        "properties_changed": {
                          "changed": {
                            "repository": {
                              "properties_changed": {
                                "removed": [
                                  "security_and_analysis"
                                ]
                              }
                            }
                          }
                        }
                      }
                    }
                  }
                }
              }
            }
          }
        }
      },
      "/repos/{owner}/{repo}/dependency-graph/compare/{basehead}": {
        "get": {
          "responses": {
            "changed": {
              "200": {
                "content": {
                  "changed": {
                    "application/json": {
                      "schema_changed": {
                        "items_changed": {
                          "properties_changed": {
                            "removed": [
                              "scope"
                            ]
                          },
                          "required_changed": {
                            "removed": [
                              "scope"
                            ]
                          }
                        }
                      }
                    }
                  }
                }
              }
            }
          }
        }
      },
      "/repos/{owner}/{repo}/forks": {
        "get": {
          "responses": {
            "changed": {
              "200": {
                "content": {
                  "changed": {
                    "application/json": {
                      "schema_changed": {
                        "items_changed": {
                          "properties_changed": {
                            "removed": [
                              "security_and_analysis"
                            ]
                          }
                        }
                      }
                    }
                  }
                }
              }
            }
          }
        }
      },
      "/repos/{owner}/{repo}/installation": {
        "get": {
          "responses": {
            "changed": {
              "200": {
                "content": {
                  "changed": {
                    "application/json": {
                      "schema_changed": {
                        "properties_changed": {
                          "changed": {
                            "permissions": {
                              "properties_changed": {
                                "removed": [
                                  "organization_announcement_banners"
                                ]
                              }
                            }
                          }
                        }
                      }
                    }
                  }
                }
              }
            }
          }
        }
      },
      "/repos/{owner}/{repo}/invitations": {
        "get": {
          "responses": {
            "changed": {
              "200": {
                "content": {
                  "changed": {
                    "application/json": {
                      "schema_changed": {
                        "items_changed": {
                          "properties_changed": {
                            "changed": {
                              "repository": {
                                "properties_changed": {
                                  "removed": [
                                    "security_and_analysis"
                                  ]
                                }
                              }
                            }
                          }
                        }
                      }
                    }
                  }
                }
              }
            }
          }
        }
      },
      "/repos/{owner}/{repo}/invitations/{invitation_id}": {
        "patch": {
          "responses": {
            "changed": {
              "200": {
                "content": {
                  "changed": {
                    "application/json": {
                      "schema_changed": {
                        "properties_changed": {
                          "changed": {
                            "repository": {
                              "properties_changed": {
                                "removed": [
                                  "security_and_analysis"
                                ]
                              }
                            }
                          }
                        }
                      }
                    }
                  }
                }
              }
            }
          }
        }
      },
      "/repos/{owner}/{repo}/notifications": {
        "get": {
          "responses": {
            "changed": {
              "200": {
                "content": {
                  "changed": {
                    "application/json": {
                      "schema_changed": {
                        "items_changed": {
                          "properties_changed": {
                            "changed": {
                              "repository": {
                                "properties_changed": {
                                  "removed": [
                                    "security_and_analysis"
                                  ]
                                }
                              }
                            }
                          }
                        }
                      }
                    }
                  }
                }
              }
            }
          }
        }
      },
      "/repos/{owner}/{repo}/pulls": {
        "post": {
          "request_body": {
            "content_changed": {
              "changed": {
                "application/json": {
                  "schema_changed": {
                    "properties_changed": {
                      "removed": [
                        "head_repo"
                      ]
                    }
                  }
                }
              }
            }
          }
        }
      },
      "/repos/{owner}/{repo}/releases": {
        "post": {
          "request_body": {
            "content_changed": {
              "changed": {
                "application/json": {
                  "schema_changed": {
                    "properties_changed": {
                      "removed": [
                        "make_latest"
                      ]
                    }
                  }
                }
              }
            }
          }
        }
      },
      "/repos/{owner}/{repo}/releases/{release_id}": {
        "patch": {
          "request_body": {
            "content_changed": {
              "changed": {
                "application/json": {
                  "schema_changed": {
                    "properties_changed": {
                      "removed": [
                        "make_latest"
                      ]
                    }
                  }
                }
              }
            }
          }
        }
      },
      "/repos/{owner}/{repo}/secret-scanning/alerts": {
        "get": {
          "responses": {
            "changed": {
              "200": {
                "content": {
                  "changed": {
                    "application/json": {
                      "schema_changed": {
                        "items_changed": {
                          "properties_changed": {
                            "removed": [
                              "resolution_comment"
                            ]
                          }
                        }
                      }
                    }
                  }
                }
              }
            }
          }
        }
      },
      "/repos/{owner}/{repo}/secret-scanning/alerts/{alert_number}": {
        "get": {
          "responses": {
            "changed": {
              "200": {
                "content": {
                  "changed": {
                    "application/json": {
                      "schema_changed": {
                        "properties_changed": {
                          "removed": [
                            "resolution_comment"
                          ]
                        }
                      }
                    }
                  }
                }
              }
            }
          }
        },
        "patch": {
          "request_body": {
            "content_changed": {
              "changed": {
                "application/json": {
                  "schema_changed": {
                    "properties_changed": {
                      "removed": [
                        "resolution_comment"
                      ]
                    }
                  }
                }
              }
            }
          },
          "responses": {
            "changed": {
              "200": {
                "content": {
                  "changed": {
                    "application/json": {
                      "schema_changed": {
                        "properties_changed": {
                          "removed": [
                            "resolution_comment"
                          ]
                        }
                      }
                    }
                  }
                }
              }
            },
            "removed": [
              "400"
            ]
          }
        }
      },
      "/repos/{owner}/{repo}/secret-scanning/alerts/{alert_number}/locations": {
        "get": {
          "responses": {
            "changed": {
              "200": {
                "content": {
                  "changed": {
                    "application/json": {
                      "schema_changed": {
                        "items_changed": {
                          "properties_changed": {
                            "changed": {
                              "type": {
                                "enum_changed": {
                                  "added": false,
                                  "removed": false,
                                  "values_removed": [
                                    "issue_title",
                                    "issue_body",
                                    "issue_comment"
                                  ]
                                }
                              }
                            }
                          }
                        }
                      }
                    }
                  }
                }
              }
            }
          }
        }
      },
      "/repos/{owner}/{repo}/transfer": {
        "post": {
          "responses": {
            "changed": {
              "202": {
                "content": {
                  "changed": {
                    "application/json": {
                      "schema_changed": {
                        "properties_changed": {
                          "removed": [
                            "security_and_analysis"
                          ]
                        }
                      }
                    }
                  }
                }
              }
            }
          }
        }
      },
      "/repositories": {
        "get": {
          "responses": {
            "changed": {
              "200": {
                "content": {
                  "changed": {
                    "application/json": {
                      "schema_changed": {
                        "items_changed": {
                          "properties_changed": {
                            "removed": [
                              "security_and_analysis"
                            ]
                          }
                        }
                      }
                    }
                  }
                }
              }
            }
          }
        }
      },
      "/search/code": {
        "get": {
          "responses": {
            "changed": {
              "200": {
                "content": {
                  "changed": {
                    "application/json": {
                      "schema_changed": {
                        "properties_changed": {
                          "changed": {
                            "items": {
                              "items_changed": {
                                "properties_changed": {
                                  "changed": {
                                    "repository": {
                                      "properties_changed": {
                                        "removed": [
                                          "security_and_analysis"
                                        ]
                                      }
                                    }
                                  }
                                }
                              }
                            }
                          }
                        }
                      }
                    }
                  }
                }
              }
            }
          }
        }
      },
      "/search/commits": {
        "get": {
          "responses": {
            "changed": {
              "200": {
                "content": {
                  "changed": {
                    "application/json": {
                      "schema_changed": {
                        "properties_changed": {
                          "changed": {
                            "items": {
                              "items_changed": {
                                "properties_changed": {
                                  "changed": {
                                    "repository": {
                                      "properties_changed": {
                                        "removed": [
                                          "security_and_analysis"
                                        ]
                                      }
                                    }
                                  }
                                }
                              }
                            }
                          }
                        }
                      }
                    }
                  }
                }
              }
            }
          }
        }
      },
      "/teams/{team_id}/repos": {
        "get": {
          "responses": {
            "changed": {
              "200": {
                "content": {
                  "changed": {
                    "application/json": {
                      "schema_changed": {
                        "items_changed": {
                          "properties_changed": {
                            "removed": [
                              "security_and_analysis"
                            ]
                          }
                        }
                      }
                    }
                  }
                }
              }
            }
          }
        }
      },
      "/user/installations": {
        "get": {
          "responses": {
            "changed": {
              "200": {
                "content": {
                  "changed": {
                    "application/json": {
                      "schema_changed": {
                        "properties_changed": {
                          "changed": {
                            "installations": {
                              "items_changed": {
                                "properties_changed": {
                                  "changed": {
                                    "permissions": {
                                      "properties_changed": {
                                        "removed": [
                                          "organization_announcement_banners"
                                        ]
                                      }
                                    }
                                  }
                                }
                              }
                            }
                          }
                        }
                      }
                    }
                  }
                }
              }
            }
          }
        }
      },
      "/user/migrations/{migration_id}/repositories": {
        "get": {
          "responses": {
            "changed": {
              "200": {
                "content": {
                  "changed": {
                    "application/json": {
                      "schema_changed": {
                        "items_changed": {
                          "properties_changed": {
                            "removed": [
                              "security_and_analysis"
                            ]
                          }
                        }
                      }
                    }
                  }
                }
              }
            }
          }
        }
      },
      "/user/repository_invitations": {
        "get": {
          "responses": {
            "changed": {
              "200": {
                "content": {
                  "changed": {
                    "application/json": {
                      "schema_changed": {
                        "items_changed": {
                          "properties_changed": {
                            "changed": {
                              "repository": {
                                "properties_changed": {
                                  "removed": [
                                    "security_and_analysis"
                                  ]
                                }
                              }
                            }
                          }
                        }
                      }
                    }
                  }
                }
              }
            }
          }
        }
      },
      "/user/subscriptions": {
        "get": {
          "responses": {
            "changed": {
              "200": {
                "content": {
                  "changed": {
                    "application/json": {
                      "schema_changed": {
                        "items_changed": {
                          "properties_changed": {
                            "removed": [
                              "security_and_analysis"
                            ]
                          }
                        }
                      }
                    }
                  }
                }
              }
            }
          }
        }
      },
      "/users/{username}/installation": {
        "get": {
          "responses": {
            "changed": {
              "200": {
                "content": {
                  "changed": {
                    "application/json": {
                      "schema_changed": {
                        "properties_changed": {
                          "changed": {
                            "permissions": {
                              "properties_changed": {
                                "removed": [
                                  "organization_announcement_banners"
                                ]
                              }
                            }
                          }
                        }
                      }
                    }
                  }
                }
              }
            }
          }
        }
      },
      "/users/{username}/repos": {
        "get": {
          "responses": {
            "changed": {
              "200": {
                "content": {
                  "changed": {
                    "application/json": {
                      "schema_changed": {
                        "items_changed": {
                          "properties_changed": {
                            "removed": [
                              "security_and_analysis"
                            ]
                          }
                        }
                      }
                    }
                  }
                }
              }
            }
          }
        }
      },
      "/users/{username}/subscriptions": {
        "get": {
          "responses": {
            "changed": {
              "200": {
                "content": {
                  "changed": {
                    "application/json": {
                      "schema_changed": {
                        "items_changed": {
                          "properties_changed": {
                            "removed": [
                              "security_and_analysis"
                            ]
                          }
                        }
                      }
                    }
                  }
                }
              }
            }
          }
        }
      }
    },
    "removed": {
      "/enterprises/{enterprise}/code_security_and_analysis": [
        "get",
        "patch"
      ],
      "/enterprises/{enterprise}/dependabot/alerts": [
        "get"
      ],
      "/enterprises/{enterprise}/{security_product}/{enablement}": [
        "post"
      ],
      "/orgs/{org}/actions/required_workflows": [
        "get",
        "post"
      ],
      "/orgs/{org}/actions/required_workflows/{required_workflow_id}": [
        "get",
        "delete",
        "patch"
      ],
      "/orgs/{org}/actions/required_workflows/{required_workflow_id}/repositories": [
        "get",
        "put"
      ],
      "/orgs/{org}/actions/required_workflows/{required_workflow_id}/repositories/{repository_id}": [
        "put",
        "delete"
      ],
      "/orgs/{org}/actions/variables": [
        "get",
        "post"
      ],
      "/orgs/{org}/actions/variables/{name}": [
        "get",
        "delete",
        "patch"
      ],
      "/orgs/{org}/actions/variables/{name}/repositories": [
        "get",
        "put"
      ],
      "/orgs/{org}/actions/variables/{name}/repositories/{repository_id}": [
        "put",
        "delete"
      ],
      "/orgs/{org}/announcement": [
        "get",
        "delete",
        "patch"
      ],
      "/orgs/{org}/dependabot/alerts": [
        "get"
      ],
      "/repos/{org}/{repo}/actions/required_workflows": [
        "get"
      ],
      "/repos/{org}/{repo}/actions/required_workflows/{required_workflow_id_for_repo}": [
        "get"
      ],
      "/repos/{owner}/{repo}/actions/required_workflows/{required_workflow_id_for_repo}/runs": [
        "get"
      ],
      "/repos/{owner}/{repo}/actions/variables": [
        "get",
        "post"
      ],
      "/repos/{owner}/{repo}/actions/variables/{name}": [
        "get",
        "delete",
        "patch"
      ],
      "/repos/{owner}/{repo}/dependabot/alerts": [
        "get"
      ],
      "/repos/{owner}/{repo}/dependabot/alerts/{alert_number}": [
        "get",
        "patch"
      ],
      "/repositories/{repository_id}/environments/{environment_name}/variables": [
        "get",
        "post"
      ],
      "/repositories/{repository_id}/environments/{environment_name}/variables/{name}": [
        "get",
        "delete",
        "patch"
      ]
    }
  }
}